retrain_pipelines/__init__.py
retrain_pipelines/__version__.py
retrain_pipelines/local_launcher.py
retrain_pipelines/local_launcher.sh
retrain_pipelines/local_launcher_magic.py
retrain_pipelines/dataset/__init__.py
retrain_pipelines/dataset/dataset.py
retrain_pipelines/dataset/tool_calls.py
retrain_pipelines/dataset/features_dependencies/__init__.py
retrain_pipelines/dataset/features_dependencies/features_dependencies.py
retrain_pipelines/dataset/hf_utils/__init__.py
retrain_pipelines/dataset/hf_utils/hacky_size_categories.py
retrain_pipelines/dataset/hf_utils/hf_utils.py
retrain_pipelines/frameworks/__init__.py
retrain_pipelines/frameworks/local_metaflow/__init__.py
retrain_pipelines/inspectors/__init__.py
retrain_pipelines/inspectors/hf.py
retrain_pipelines/inspectors/hp_cv_inspector.py
retrain_pipelines/inspectors/utils.py
retrain_pipelines/inspectors/wandb.py
retrain_pipelines/model/__init__.py
retrain_pipelines/model/hf_utils.py
retrain_pipelines/model/mf_lightgbm_regress_tempo/__init__.py
retrain_pipelines/model/mf_lightgbm_regress_tempo/dask_trainer.py
retrain_pipelines/model/mf_lightgbm_regress_tempo/preprocessing.py
retrain_pipelines/model/mf_lightgbm_regress_tempo/tempo_helpers.py
retrain_pipelines/model/mf_lightgbm_regress_tempo/tempo_model.py
retrain_pipelines/model/mf_tabnet_classif_torchserve/Dockerfile.torchserve
retrain_pipelines/model/mf_tabnet_classif_torchserve/__init__.py
retrain_pipelines/model/mf_tabnet_classif_torchserve/preprocessing.py
retrain_pipelines/model/mf_tabnet_classif_torchserve/torchserve_tabnet_handler.py
retrain_pipelines/model/mf_tabnet_classif_torchserve/trainer_utils.py
retrain_pipelines/model/mf_tabnet_classif_torchserve/endpoint_test/__init__.py
retrain_pipelines/model/mf_tabnet_classif_torchserve/endpoint_test/endpoint_test.py
retrain_pipelines/model/mf_tabnet_classif_torchserve/torchserve/__init__.py
retrain_pipelines/model/mf_tabnet_classif_torchserve/torchserve/model_info.py
retrain_pipelines-0.1.2.dist-info/licenses/LICENSE
retrain_pipelines-0.1.2.dist-info/METADATA
retrain_pipelines-0.1.2.dist-info/WHEEL
retrain_pipelines-0.1.2.dist-info/entry_points.txt
retrain_pipelines-0.1.2.dist-info/top_level.txt
retrain_pipelines-0.1.2.dist-info/RECORD
