Metadata-Version: 2.4
Name: retrain-pipelines
Version: 0.1.2
Summary: retrain-pipelines lowers the barrier to entry for the creation and management of professional machine learning retraining pipelines.
Author: Aurelien-Morgan
Maintainer: Aurelien-Morgan
License: Apache License 2.0
Project-URL: Repository, https://github.com/aurelienmorgan/retrain-pipelines
Project-URL: PyPI, https://pypi.org/project/retrain-pipelines/
Project-URL: Hugging Face, https://huggingface.co/retrain-pipelines
Keywords: machine-learning,ml-pipelines,retrain-pipelines,model-retraining,automl,mlops,model-versioning,model-blessing,inference-pipeline,docker-deployment,data-preprocessing,hyperparameter-tuning,model-performance,pipeline-documentation,eda,exploratory-data-analysis,continuous-integration,continuous-deployment,ci-cd,model-monitoring,pipeline-customization,pipeline-templates,open-source
Classifier: Development Status :: 4 - Beta
Classifier: Programming Language :: Python :: 3
Classifier: License :: OSI Approved :: Apache Software License
Classifier: Intended Audience :: Developers
Classifier: Operating System :: OS Independent
Classifier: Topic :: Software Development :: Documentation
Classifier: Topic :: Software Development :: Quality Assurance
Classifier: Topic :: Software Development :: Version Control
Classifier: Topic :: Scientific/Engineering :: Artificial Intelligence
Classifier: Topic :: Utilities
Requires-Python: >=3.3
License-File: LICENSE
Requires-Dist: ipykernel>=6.20
Requires-Dist: pandas>=2
Requires-Dist: matplotlib>=3.4
Requires-Dist: metaflow>=2.9
Requires-Dist: wandb>0.15
Requires-Dist: plotly>=4
Requires-Dist: jinja2>=3
Requires-Dist: scikit-learn>=1
Requires-Dist: numpy<2,>=1.17.3
Requires-Dist: regex>=2022.10.31
Requires-Dist: colorama>=0.4
Dynamic: license-file
